pybedquilt/__init__.py
pybedquilt/core.py
pybedquilt-1.1.0.dist-info/DESCRIPTION.rst
pybedquilt-1.1.0.dist-info/METADATA
pybedquilt-1.1.0.dist-info/RECORD
pybedquilt-1.1.0.dist-info/WHEEL
pybedquilt-1.1.0.dist-info/metadata.json
pybedquilt-1.1.0.dist-info/top_level.txt
