Metadata-Version: 2.0
Name: pybedquilt
Version: 1.1.0
Summary: A Python driver for BedquiltDB.
Home-page: https://github.com/BedquiltDB/pybedquilt
Author: Shane Kilkelly
Author-email: shane@kilkelly.me
License: MIT
Keywords: bedquilt bedquiltdb database json json-store
Platform: UNKNOWN
Classifier: Development Status :: 4 - Beta
Classifier: Intended Audience :: Developers
Classifier: Topic :: Database :: Front-Ends
Classifier: License :: OSI Approved :: MIT License
Classifier: Programming Language :: Python :: 2
Classifier: Programming Language :: Python :: 2.6
Classifier: Programming Language :: Python :: 2.7
Classifier: Programming Language :: Python :: 3
Classifier: Programming Language :: Python :: 3.4
Classifier: Programming Language :: Python :: 3.5
Requires-Dist: psycopg2
Requires-Dist: six
Provides-Extra: dev
Requires-Dist: check-manifest; extra == 'dev'
Provides-Extra: test
Requires-Dist: coverage; extra == 'test'
